geometry_p/__init__.py
geometry_p/figure.py
geometry_p/point.py
geometry_p-0.0.1.dist-info/METADATA
geometry_p-0.0.1.dist-info/WHEEL
geometry_p-0.0.1.dist-info/top_level.txt
geometry_p-0.0.1.dist-info/RECORD
