Metadata-Version: 2.1
Name: geometry-p
Version: 0.0.1
Summary: This is the simplest module for quick work with files.
Author: me
Author-email: example@gmail.com
Requires-Dist: requests (>=2.25.1)
